odoo/addons/hotel/README.rst
odoo/addons/hotel/__init__.py
odoo/addons/hotel/__manifest__.py
odoo/addons/hotel/data/hotel_sequence.xml
odoo/addons/hotel/demo/hotel_data.xml
odoo/addons/hotel/i18n/bg.po
odoo/addons/hotel/i18n/da.po
odoo/addons/hotel/i18n/es.po
odoo/addons/hotel/i18n/fr.po
odoo/addons/hotel/i18n/fr_BE.po
odoo/addons/hotel/i18n/hotel.pot
odoo/addons/hotel/i18n/hr.po
odoo/addons/hotel/i18n/it.po
odoo/addons/hotel/i18n/pt_BR.po
odoo/addons/hotel/i18n/sv.po
odoo/addons/hotel/i18n/zh_CN.po
odoo/addons/hotel/models/__init__.py
odoo/addons/hotel/models/account_move.py
odoo/addons/hotel/models/hotel_folio.py
odoo/addons/hotel/models/hotel_room.py
odoo/addons/hotel/models/hotel_services.py
odoo/addons/hotel/models/product_product.py
odoo/addons/hotel/models/res_company.py
odoo/addons/hotel/readme/CONTRIBUTORS.rst
odoo/addons/hotel/readme/DESCRIPTION.rst
odoo/addons/hotel/report/__init__.py
odoo/addons/hotel/report/hotel_folio_report_template.xml
odoo/addons/hotel/report/hotel_report.py
odoo/addons/hotel/report/report_view.xml
odoo/addons/hotel/security/hotel_security.xml
odoo/addons/hotel/security/ir.model.access.csv
odoo/addons/hotel/static/description/Hotel.png
odoo/addons/hotel/static/description/bed.png
odoo/addons/hotel/static/description/book.png
odoo/addons/hotel/static/description/booking.png
odoo/addons/hotel/static/description/car.png
odoo/addons/hotel/static/description/checkin.png
odoo/addons/hotel/static/description/currency.png
odoo/addons/hotel/static/description/fast-food-icons.png
odoo/addons/hotel/static/description/gym.png
odoo/addons/hotel/static/description/head.png
odoo/addons/hotel/static/description/hotel1.png
odoo/addons/hotel/static/description/hotel2.png
odoo/addons/hotel/static/description/icon-book.png
odoo/addons/hotel/static/description/icon.png
odoo/addons/hotel/static/description/inc1.png
odoo/addons/hotel/static/description/inc2.png
odoo/addons/hotel/static/description/inc3.png
odoo/addons/hotel/static/description/inc4.png
odoo_addon_hotel-16.0.1.0.0.28.dist-info/METADATA
odoo_addon_hotel-16.0.1.0.0.28.dist-info/WHEEL
odoo_addon_hotel-16.0.1.0.0.28.dist-info/top_level.txt
odoo_addon_hotel-16.0.1.0.0.28.dist-info/RECORD
