Metadata-Version: 2.1
Name: odoo-addon-hotel
Version: 16.0.1.0.0.28
Summary: Hotel Management to Manage Folio and Hotel Configuration
Home-page: https://github.com/OCA/vertical-hotel
Author: Odoo Community Association (OCA), Serpent Consulting Services Pvt. Ltd., OpenERP SA
Author-email: support@odoo-community.org
License: LGPL-3
Classifier: Programming Language :: Python
Classifier: Framework :: Odoo
Classifier: Framework :: Odoo :: 16.0
Classifier: License :: OSI Approved :: GNU Lesser General Public License v3 (LGPLv3)
Requires-Python: >=3.10
Requires-Dist: odoo<16.1dev,>=16.0a
Requires-Dist: python-dateutil
